hy2d/__init__.py
hy2d/logging_config.py
hy2d/main.py
hy2d/py.typed
hy2d/cli/__init__.py
hy2d/cli/check.py
hy2d/cli/install.py
hy2d/cli/log.py
hy2d/cli/remove.py
hy2d/cli/self_.py
hy2d/cli/start.py
hy2d/cli/stop.py
hy2d/cli/update.py
hy2d/core/__init__.py
hy2d/core/constants.py
hy2d/core/manager.py
hy2d/core/utils.py
heyhy-0.1.9.post1.dist-info/METADATA
heyhy-0.1.9.post1.dist-info/WHEEL
heyhy-0.1.9.post1.dist-info/entry_points.txt
heyhy-0.1.9.post1.dist-info/licenses/LICENSE
heyhy-0.1.9.post1.dist-info/RECORD
