Metadata-Version: 2.4
Name: heyhy
Version: 0.1.9.post1
Summary: mihomo-hysteria2-inbound manager
Author-email: QIN2DIM <yaoqinse@gmail.com>
License-File: LICENSE
Requires-Python: >=3.10
Requires-Dist: pyyaml>=6.0.2
Requires-Dist: typer>=0.16.0
